AnnotationCheckerWithStructure/__init__.py
AnnotationCheckerWithStructure/main.py
bioinformatics_script-0.1.2.dist-info/LICENSE
bioinformatics_script-0.1.2.dist-info/METADATA
bioinformatics_script-0.1.2.dist-info/WHEEL
bioinformatics_script-0.1.2.dist-info/entry_points.txt
bioinformatics_script-0.1.2.dist-info/top_level.txt
bioinformatics_script-0.1.2.dist-info/RECORD
